drf_spectacular_jsonapi/__init__.py
drf_spectacular_jsonapi/apps.py
drf_spectacular_jsonapi/hooks.py
drf_spectacular_jsonapi/schemas/__init__.py
drf_spectacular_jsonapi/schemas/converters.py
drf_spectacular_jsonapi/schemas/openapi.py
drf_spectacular_jsonapi/schemas/pagination.py
drf_spectacular_jsonapi/schemas/plumbing.py
drf_spectacular_jsonapi/schemas/utils.py
drf_spectacular_jsonapi-0.5.2.dist-info/LICENSE
drf_spectacular_jsonapi-0.5.2.dist-info/METADATA
drf_spectacular_jsonapi-0.5.2.dist-info/WHEEL
drf_spectacular_jsonapi-0.5.2.dist-info/top_level.txt
drf_spectacular_jsonapi-0.5.2.dist-info/RECORD
