Metadata-Version: 2.1
Name: drf-spectacular-jsonapi
Version: 0.5.2
Summary: open api 3 schema generator for drf-json-api package based on drf-spectacular package.
Home-page: https://github.com/jokiefer/drf-spectecular-json-api
Author: Jonas Kiefer
Author-email: jonas.kiefer@live.com
License: BSD
Platform: UNKNOWN
Classifier: Development Status :: 3 - Alpha
Classifier: Intended Audience :: Developers
Classifier: Natural Language :: English
Classifier: Programming Language :: Python :: 3.7
Classifier: Programming Language :: Python :: 3.8
Classifier: Programming Language :: Python :: 3.9
Classifier: Programming Language :: Python :: 3.10
Classifier: Programming Language :: Python :: 3.11
Classifier: Topic :: Internet :: WWW/HTTP
Classifier: Environment :: Web Environment
Classifier: Framework :: Django
Classifier: Topic :: Software Development :: Libraries
Classifier: License :: OSI Approved :: BSD License
Classifier: Operating System :: OS Independent
Classifier: Topic :: Internet :: WWW/HTTP
Classifier: Topic :: Documentation
Classifier: Topic :: Software Development :: Code Generators
Requires-Python: >=3.7
License-File: LICENSE
Requires-Dist: Django (>=3.2)
Requires-Dist: djangorestframework-jsonapi (>=6.0.0)
Requires-Dist: djangorestframework (>=3.13)
Requires-Dist: drf-extensions (>=0.7.1)
Requires-Dist: drf-spectacular (>=0.25.0)
